ragbox/__init__.py
ragbox/cli.py
ragbox/config.py
ragbox/rag_engine.py
ragbox-0.1.1.dist-info/METADATA
ragbox-0.1.1.dist-info/WHEEL
ragbox-0.1.1.dist-info/entry_points.txt
ragbox-0.1.1.dist-info/top_level.txt
ragbox-0.1.1.dist-info/RECORD
