Metadata-Version: 2.4
Name: ragbox
Version: 0.1.1
Summary: A command-line RAG tool for querying documents using LlamaIndex with OpenAI and Ollama support
Author-email: Pray Apostel Simanjuntak <simanjuntakpray@gmail.com>
License: MIT
Project-URL: Homepage, https://github.com/praysimanjuntak/ragbox
Project-URL: Repository, https://github.com/praysimanjuntak/ragbox
Project-URL: Issues, https://github.com/praysimanjuntak/ragbox/issues
Keywords: rag,llm,cli,llamaindex,ollama,openai,question-answering,documents
Classifier: Development Status :: 3 - Alpha
Classifier: Intended Audience :: Developers
Classifier: License :: OSI Approved :: MIT License
Classifier: Programming Language :: Python :: 3
Classifier: Programming Language :: Python :: 3.8
Classifier: Programming Language :: Python :: 3.9
Classifier: Programming Language :: Python :: 3.10
Classifier: Programming Language :: Python :: 3.11
Classifier: Programming Language :: Python :: 3.12
Requires-Python: >=3.8
Requires-Dist: llama-index-core>=0.14.0
Requires-Dist: llama-index-embeddings-openai>=0.3.0
Requires-Dist: llama-index-embeddings-ollama>=0.3.0
Requires-Dist: llama-index-llms-ollama>=0.8.0
Requires-Dist: llama-index-llms-openai>=0.3.0
Provides-Extra: dev
Requires-Dist: pytest>=7.0.0; extra == "dev"
Requires-Dist: black>=23.0.0; extra == "dev"
Requires-Dist: isort>=5.0.0; extra == "dev"
Requires-Dist: mypy>=1.0.0; extra == "dev"
